CorpusToolkit/__init__.py
CorpusToolkit/cleaner.py
CorpusToolkit/config.py
CorpusToolkit/duplicates.py
CorpusToolkit/splitter.py
CorpusToolkit/utils.py
CorpusToolkit/scorer/__init__.py
CorpusToolkit/scorer/fluency.py
corpuskit-0.1.1.dist-info/METADATA
corpuskit-0.1.1.dist-info/WHEEL
corpuskit-0.1.1.dist-info/licenses/LICENSE.txt
corpuskit-0.1.1.dist-info/RECORD
