Metadata-Version: 2.4
Name: CorpusKit
Version: 0.1.1
Summary: Corpus analysis and processing toolkit
Author-email: Morton Li <Morton.L@Outlook.com>
License: Apache-2.0
License-File: LICENSE.txt
Keywords: NLP,corpus,natural language processing,text analysis,text cleaning,text processing
Classifier: License :: OSI Approved :: Apache Software License
Classifier: Programming Language :: Python :: 3.9
Classifier: Programming Language :: Python :: 3.10
Classifier: Programming Language :: Python :: 3.11
Classifier: Programming Language :: Python :: 3.12
Classifier: Programming Language :: Python :: 3.13
Requires-Python: >=3.9
Requires-Dist: datasketch~=1.6.5
Requires-Dist: pandas~=2.2.3
Requires-Dist: pyarrow~=20.0.0
Requires-Dist: tqdm~=4.67.1
Provides-Extra: dev
Provides-Extra: ml
Requires-Dist: accelerate~=1.7.0; extra == 'ml'
Requires-Dist: torch~=2.7.0; extra == 'ml'
Requires-Dist: transformers~=4.52.3; extra == 'ml'
